tddflow/__init__.py
tddflow/__main__.py
tddflow/testing.py
tddflow/watch.bsh
tddflow/_internal/__init__.py
tddflow/_internal/assert_.py
tddflow/_internal/assert_test.py
tddflow/_internal/reporting.py
tddflow/_internal/reporting_test.py
tddflow/_internal/runall.bsh
tddflow/_internal/testcontext.py
tddflow/_internal/testfixtures.py
tddflow/_internal/testing_test.py
tddflow/_internal/testmocks.py
tddflow/_internal/tui.py
tddflow/_internal/watcher.py
tddflow/_internal/watcher_test.py
tddflow/_internal/watchergolden/__init__.py
tddflow/_internal/watchergolden/context.py
tddflow/_internal/watchergolden/pm1.py
tddflow/_internal/watchergolden/pm2.py
tddflow/_internal/watchergolden/suffix_test.py
tddflow/_internal/watchergolden/test_prefix.py
tddflow/_internal/watchergolden/failed/__init__.py
tddflow/_internal/watchergolden/failed/compile_test.py
tddflow/_internal/watchergolden/failed/context.py
tddflow/_internal/watchergolden/flat/__init__.py
tddflow/_internal/watchergolden/flat/is_better/__init__.py
tddflow/_internal/watchergolden/flat/is_better/nest.py
tddflow/_internal/watchergolden/flat/is_better/than_nested/__init__.py
tddflow/_internal/watchergolden/flat/is_better/than_nested/deep.py
tddflow/_internal/watchergolden/tests/__init__.py
tddflow/_internal/watchergolden/tests/context.py
tddflow/_internal/watchergolden/tests/suffix_dir_test.py
tddflow/_internal/watchergolden/tests/test_prefix_dir.py
tddflow-0.9.1.dist-info/METADATA
tddflow-0.9.1.dist-info/WHEEL
tddflow-0.9.1.dist-info/licenses/LICENSE.txt
tddflow-0.9.1.dist-info/RECORD
