Metadata-Version: 2.1
Name: tddflow
Version: 0.9.1
Summary: simple, lightweight python testing framework for a TDD workflow with automatic test execution
Project-URL: Homepage, https://github.com/slukits/tddflow
Project-URL: Bug Tracker, https://github.com/slukits/tddflow/issues
Author-email: Stephan Lukits <stephan.lukits@gmail.com>
License-File: LICENSE.txt
Classifier: License :: OSI Approved :: MIT License
Classifier: Operating System :: OS Independent
Classifier: Programming Language :: Python :: 3
Requires-Python: >=3.10
